setup.cfg
setup.py
sqla_hierarchy/__init__.py
sqla_hierarchy/hierarchy.py
sqla_hierarchy.egg-info/PKG-INFO
sqla_hierarchy.egg-info/SOURCES.txt
sqla_hierarchy.egg-info/dependency_links.txt
sqla_hierarchy.egg-info/requires.txt
sqla_hierarchy.egg-info/top_level.txt