Metadata-Version: 1.0
Name: sqla-hierarchy
Version: 0.1
Summary: Adjacency List Relationships helper (only using databases own implementations)
Home-page: https://github.com/marplatense/sqla_hierarchy
Author: Mariano Mara
Author-email: mariano.mara@gmail.com
License: MIT License
Download-URL: https://github.com/marplatense/sqla_hierarchy/downloads
Keywords: sqlachemy,hierarchy,adjacency list,python
Platform: UNKNOWN
Classifier: Development Status :: 4 - Beta
Classifier: Intended Audience :: Developers
Classifier: License :: OSI Approved :: MIT License
Classifier: Operating System :: OS Independent
Classifier: Programming Language :: Python
Classifier: Topic :: Software Development :: Libraries :: Python Modules
